snooze/__init__.py
snooze/__main__.py
snooze/alerta/syslogfwder.py
snooze/api/__init__.py
snooze/api/base.py
snooze/api/falcon.py
snooze/api/socket.py
snooze/api/static.py
snooze/api/tcp.py
snooze/cli/__init__.py
snooze/cli/__main__.py
snooze/cli/health.py
snooze/cli/login.py
snooze/cli/record.py
snooze/cli/root_token.py
snooze/cli/snooze.py
snooze/core.py
snooze/db/__init__.py
snooze/db/database.py
snooze/db/file/__init__.py
snooze/db/file/database.py
snooze/db/mongo/__init__.py
snooze/db/mongo/database.py
snooze/defaults/core.yaml
snooze/defaults/general.yaml
snooze/defaults/housekeeping.yaml
snooze/defaults/ldap_auth.yaml
snooze/defaults/logging.yaml
snooze/defaults/logging_file.yaml
snooze/defaults/notifications.yaml
snooze/defaults/web/action.yaml
snooze/defaults/web/aggregaterule.yaml
snooze/defaults/web/alert.yaml
snooze/defaults/web/environment.yaml
snooze/defaults/web/kv.yaml
snooze/defaults/web/notification.yaml
snooze/defaults/web/profile.yaml
snooze/defaults/web/role.yaml
snooze/defaults/web/rule.yaml
snooze/defaults/web/settings.yaml
snooze/defaults/web/snooze.yaml
snooze/defaults/web/user.yaml
snooze/defaults/web/widget.yaml
snooze/health.py
snooze/plugins/__init__.py
snooze/plugins/core/__init__.py
snooze/plugins/core/action/__init__.py
snooze/plugins/core/action/falcon/__init__.py
snooze/plugins/core/action/falcon/route.py
snooze/plugins/core/action/metadata.yaml
snooze/plugins/core/action/plugin.py
snooze/plugins/core/aggregaterule/__init__.py
snooze/plugins/core/aggregaterule/metadata.yaml
snooze/plugins/core/aggregaterule/plugin.py
snooze/plugins/core/audit/__init__.py
snooze/plugins/core/audit/metadata.yaml
snooze/plugins/core/basic/__init__.py
snooze/plugins/core/basic/falcon/__init__.py
snooze/plugins/core/basic/falcon/route.py
snooze/plugins/core/basic/plugin.py
snooze/plugins/core/comment/__init__.py
snooze/plugins/core/comment/falcon/__init__.py
snooze/plugins/core/comment/falcon/route.py
snooze/plugins/core/comment/metadata.yaml
snooze_server-1.4.1.dist-info/entry_points.txt
snooze_server-1.4.1.dist-info/LICENSE
snooze_server-1.4.1.dist-info/WHEEL
snooze_server-1.4.1.dist-info/METADATA
snooze_server-1.4.1.dist-info/RECORD
