Metadata-Version: 2.1
Name: snooze-server
Version: 1.4.1
Summary: Monitoring tool for logs aggregation and alerting
License: AGPL-3.0-or-later
Author: Florian Dematraz
Author-email: florian.dematraz@snoozeweb.net
Requires-Python: >=3.6,<4.0
Classifier: License :: OSI Approved :: GNU Affero General Public License v3 or later (AGPLv3+)
Classifier: Programming Language :: Python :: 3
Classifier: Programming Language :: Python :: 3.6
Classifier: Programming Language :: Python :: 3.7
Classifier: Programming Language :: Python :: 3.8
Classifier: Programming Language :: Python :: 3.9
Classifier: Programming Language :: Python :: 3.10
Requires-Dist: Jinja2 (>=3.0.1,<4.0.0)
Requires-Dist: MarkupSafe (>=2.0.1,<3.0.0)
Requires-Dist: PyJWT (==1.7.1)
Requires-Dist: PyYAML (==5.4.1)
Requires-Dist: click (>=8.0.1,<9.0.0)
Requires-Dist: dataclasses (>=0.8,<0.9); python_version >= "3.6" and python_version < "3.7"
Requires-Dist: falcon (>=3.0.1,<4.0.0)
Requires-Dist: falcon-auth (>=1.1.0,<2.0.0)
Requires-Dist: importlib-metadata (>=4.8.1,<5.0.0)
Requires-Dist: kombu (==5.1.0)
Requires-Dist: ldap3 (>=2.9.1,<3.0.0)
Requires-Dist: netifaces (>=0.11.0,<0.12.0)
Requires-Dist: pathlib (>=1.0.1,<2.0.0)
Requires-Dist: prometheus-client (>=0.13.1,<0.14.0)
Requires-Dist: pymongo (==3.12.1)
Requires-Dist: pyparsing (>=2.4.7,<3.0.0)
Requires-Dist: python-dateutil (>=2.8.2,<3.0.0)
Requires-Dist: requests (>=2.26.0,<3.0.0)
Requires-Dist: requests-unixsocket (>=0.2.0,<0.3.0)
Requires-Dist: tinydb (==4.5.2)
Requires-Dist: typing-extensions (>=3.10.0.2,<4.0.0.0)
Requires-Dist: waitress (>=2.0.0,<3.0.0)
